{
  "scriptId": "307",
  "url": "file:///Users/david/dev/deno_std/expect/_format_test.ts",
  "functions": [
    {
      "functionName": "",
      "ranges": [{ "startOffset": 0, "endOffset": 2917, "count": 1 }],
      "isBlockCoverage": true
    },
    {
      "functionName": "",
      "ranges": [{ "startOffset": 339, "endOffset": 589, "count": 1 }],
      "isBlockCoverage": true
    },
    {
      "functionName": "",
      "ranges": [{ "startOffset": 360, "endOffset": 460, "count": 1 }],
      "isBlockCoverage": true
    },
    {
      "functionName": "",
      "ranges": [{ "startOffset": 784, "endOffset": 1872, "count": 1 }],
      "isBlockCoverage": true
    },
    {
      "functionName": "",
      "ranges": [{ "startOffset": 986, "endOffset": 1080, "count": 1 }],
      "isBlockCoverage": true
    },
    {
      "functionName": "",
      "ranges": [{ "startOffset": 1136, "endOffset": 1291, "count": 1 }],
      "isBlockCoverage": true
    },
    {
      "functionName": "get",
      "ranges": [{ "startOffset": 1223, "endOffset": 1257, "count": 1 }],
      "isBlockCoverage": true
    },
    {
      "functionName": "",
      "ranges": [{ "startOffset": 1348, "endOffset": 1613, "count": 1 }],
      "isBlockCoverage": true
    },
    {
      "functionName": "",
      "ranges": [{ "startOffset": 1688, "endOffset": 1868, "count": 1 }],
      "isBlockCoverage": true
    },
    {
      "functionName": "",
      "ranges": [{ "startOffset": 1937, "endOffset": 2914, "count": 1 }],
      "isBlockCoverage": true
    }
  ]
}
