{
  "scriptId": "307",
  "url": "file:///Users/david/dev/deno_std/data_structures/binary_heap_test.ts",
  "functions": [
    {
      "functionName": "",
      "ranges": [{ "startOffset": 0, "endOffset": 11992, "count": 1 }],
      "isBlockCoverage": true
    },
    {
      "functionName": "",
      "ranges": [
        { "startOffset": 336, "endOffset": 1761, "count": 1 },
        { "startOffset": 782, "endOffset": 833, "count": 11 },
        { "startOffset": 950, "endOffset": 1185, "count": 11 },
        { "startOffset": 1498, "endOffset": 1725, "count": 11 }
      ],
      "isBlockCoverage": true
    },
    {
      "functionName": "",
      "ranges": [
        { "startOffset": 1817, "endOffset": 3248, "count": 1 },
        { "startOffset": 2269, "endOffset": 2320, "count": 11 },
        { "startOffset": 2437, "endOffset": 2672, "count": 11 },
        { "startOffset": 2985, "endOffset": 3212, "count": 11 }
      ],
      "isBlockCoverage": true
    },
    {
      "functionName": "",
      "ranges": [
        { "startOffset": 3292, "endOffset": 4375, "count": 1 },
        { "startOffset": 3488, "endOffset": 3730, "count": 9 },
        { "startOffset": 3973, "endOffset": 4303, "count": 9 }
      ],
      "isBlockCoverage": true
    },
    {
      "functionName": "",
      "ranges": [{ "startOffset": 3328, "endOffset": 3354, "count": 32 }],
      "isBlockCoverage": true
    },
    {
      "functionName": "",
      "ranges": [{ "startOffset": 4426, "endOffset": 5802, "count": 1 }],
      "isBlockCoverage": true
    },
    {
      "functionName": "map",
      "ranges": [{ "startOffset": 5022, "endOffset": 5032, "count": 11 }],
      "isBlockCoverage": true
    },
    {
      "functionName": "",
      "ranges": [{ "startOffset": 5086, "endOffset": 5096, "count": 11 }],
      "isBlockCoverage": true
    },
    {
      "functionName": "map",
      "ranges": [{ "startOffset": 5173, "endOffset": 5226, "count": 11 }],
      "isBlockCoverage": true
    },
    {
      "functionName": "",
      "ranges": [{ "startOffset": 5339, "endOffset": 5349, "count": 11 }],
      "isBlockCoverage": true
    },
    {
      "functionName": "map",
      "ranges": [{ "startOffset": 5418, "endOffset": 5428, "count": 11 }],
      "isBlockCoverage": true
    },
    {
      "functionName": "",
      "ranges": [{ "startOffset": 5532, "endOffset": 5542, "count": 11 }],
      "isBlockCoverage": true
    },
    {
      "functionName": "map",
      "ranges": [{ "startOffset": 5611, "endOffset": 5664, "count": 11 }],
      "isBlockCoverage": true
    },
    {
      "functionName": "",
      "ranges": [{ "startOffset": 5787, "endOffset": 5797, "count": 11 }],
      "isBlockCoverage": true
    },
    {
      "functionName": "",
      "ranges": [{ "startOffset": 5871, "endOffset": 7494, "count": 1 }],
      "isBlockCoverage": true
    },
    {
      "functionName": "map",
      "ranges": [{ "startOffset": 6558, "endOffset": 6568, "count": 11 }],
      "isBlockCoverage": true
    },
    {
      "functionName": "",
      "ranges": [{ "startOffset": 6670, "endOffset": 6680, "count": 11 }],
      "isBlockCoverage": true
    },
    {
      "functionName": "map",
      "ranges": [{ "startOffset": 6785, "endOffset": 6838, "count": 11 }],
      "isBlockCoverage": true
    },
    {
      "functionName": "",
      "ranges": [{ "startOffset": 6959, "endOffset": 6969, "count": 11 }],
      "isBlockCoverage": true
    },
    {
      "functionName": "map",
      "ranges": [{ "startOffset": 7066, "endOffset": 7076, "count": 11 }],
      "isBlockCoverage": true
    },
    {
      "functionName": "",
      "ranges": [{ "startOffset": 7188, "endOffset": 7198, "count": 11 }],
      "isBlockCoverage": true
    },
    {
      "functionName": "map",
      "ranges": [{ "startOffset": 7295, "endOffset": 7348, "count": 11 }],
      "isBlockCoverage": true
    },
    {
      "functionName": "",
      "ranges": [{ "startOffset": 7479, "endOffset": 7489, "count": 11 }],
      "isBlockCoverage": true
    },
    {
      "functionName": "",
      "ranges": [{ "startOffset": 7554, "endOffset": 9186, "count": 1 }],
      "isBlockCoverage": true
    },
    {
      "functionName": "map",
      "ranges": [{ "startOffset": 8248, "endOffset": 8258, "count": 11 }],
      "isBlockCoverage": true
    },
    {
      "functionName": "",
      "ranges": [{ "startOffset": 8360, "endOffset": 8370, "count": 11 }],
      "isBlockCoverage": true
    },
    {
      "functionName": "map",
      "ranges": [{ "startOffset": 8475, "endOffset": 8528, "count": 11 }],
      "isBlockCoverage": true
    },
    {
      "functionName": "",
      "ranges": [{ "startOffset": 8649, "endOffset": 8659, "count": 11 }],
      "isBlockCoverage": true
    },
    {
      "functionName": "map",
      "ranges": [{ "startOffset": 8757, "endOffset": 8767, "count": 11 }],
      "isBlockCoverage": true
    },
    {
      "functionName": "",
      "ranges": [{ "startOffset": 8879, "endOffset": 8889, "count": 11 }],
      "isBlockCoverage": true
    },
    {
      "functionName": "map",
      "ranges": [{ "startOffset": 8987, "endOffset": 9040, "count": 11 }],
      "isBlockCoverage": true
    },
    {
      "functionName": "",
      "ranges": [{ "startOffset": 9171, "endOffset": 9181, "count": 11 }],
      "isBlockCoverage": true
    },
    {
      "functionName": "",
      "ranges": [{ "startOffset": 9233, "endOffset": 9516, "count": 1 }],
      "isBlockCoverage": true
    },
    {
      "functionName": "",
      "ranges": [{ "startOffset": 9563, "endOffset": 9905, "count": 1 }],
      "isBlockCoverage": true
    },
    {
      "functionName": "",
      "ranges": [{ "startOffset": 9602, "endOffset": 9626, "count": 3 }],
      "isBlockCoverage": true
    },
    {
      "functionName": "",
      "ranges": [{ "startOffset": 9952, "endOffset": 10542, "count": 1 }],
      "isBlockCoverage": true
    },
    {
      "functionName": "",
      "ranges": [{ "startOffset": 9991, "endOffset": 10015, "count": 17 }],
      "isBlockCoverage": true
    },
    {
      "functionName": "",
      "ranges": [{ "startOffset": 10592, "endOffset": 11431, "count": 1 }],
      "isBlockCoverage": true
    },
    {
      "functionName": "",
      "ranges": [{ "startOffset": 11135, "endOffset": 11170, "count": 7 }],
      "isBlockCoverage": true
    },
    {
      "functionName": "",
      "ranges": [{ "startOffset": 11468, "endOffset": 11716, "count": 1 }],
      "isBlockCoverage": true
    },
    {
      "functionName": "",
      "ranges": [{ "startOffset": 11680, "endOffset": 11711, "count": 11 }],
      "isBlockCoverage": true
    },
    {
      "functionName": "",
      "ranges": [{ "startOffset": 11751, "endOffset": 11989, "count": 1 }],
      "isBlockCoverage": true
    }
  ]
}
