{
  "scriptId": "313",
  "url": "file:///Users/david/dev/deno_std/webgpu/describe_texture_format.ts",
  "functions": [
    {
      "functionName": "",
      "ranges": [{ "startOffset": 0, "endOffset": 19288, "count": 1 }],
      "isBlockCoverage": true
    },
    {
      "functionName": "describeTextureFormat",
      "ranges": [
        { "startOffset": 808, "endOffset": 19287, "count": 2 },
        { "startOffset": 883, "endOffset": 1058, "count": 0 },
        { "startOffset": 1063, "endOffset": 1233, "count": 0 },
        { "startOffset": 1238, "endOffset": 1411, "count": 0 },
        { "startOffset": 1416, "endOffset": 1589, "count": 0 },
        { "startOffset": 1594, "endOffset": 1768, "count": 0 },
        { "startOffset": 1773, "endOffset": 1947, "count": 0 },
        { "startOffset": 1952, "endOffset": 2128, "count": 0 },
        { "startOffset": 2133, "endOffset": 2309, "count": 0 },
        { "startOffset": 2314, "endOffset": 2490, "count": 0 },
        { "startOffset": 2495, "endOffset": 2669, "count": 0 },
        { "startOffset": 2674, "endOffset": 2843, "count": 0 },
        { "startOffset": 2848, "endOffset": 3020, "count": 0 },
        { "startOffset": 3025, "endOffset": 3197, "count": 0 },
        { "startOffset": 3202, "endOffset": 3389, "count": 0 },
        { "startOffset": 3394, "endOffset": 3569, "count": 0 },
        { "startOffset": 3574, "endOffset": 3749, "count": 0 },
        { "startOffset": 3754, "endOffset": 3931, "count": 0 },
        { "startOffset": 3936, "endOffset": 4112, "count": 0 },
        { "startOffset": 4117, "endOffset": 4300, "count": 0 },
        { "startOffset": 4305, "endOffset": 4480, "count": 0 },
        { "startOffset": 4485, "endOffset": 4659, "count": 0 },
        { "startOffset": 4664, "endOffset": 4838, "count": 0 },
        { "startOffset": 4843, "endOffset": 5021, "count": 0 },
        { "startOffset": 5214, "endOffset": 5389, "count": 0 },
        { "startOffset": 5394, "endOffset": 5574, "count": 0 },
        { "startOffset": 5579, "endOffset": 5755, "count": 0 },
        { "startOffset": 5760, "endOffset": 5933, "count": 0 },
        { "startOffset": 5938, "endOffset": 6111, "count": 0 },
        { "startOffset": 6116, "endOffset": 6304, "count": 0 },
        { "startOffset": 6309, "endOffset": 6484, "count": 0 },
        { "startOffset": 6489, "endOffset": 6664, "count": 0 },
        { "startOffset": 6669, "endOffset": 6846, "count": 0 },
        { "startOffset": 6851, "endOffset": 7027, "count": 0 },
        { "startOffset": 7032, "endOffset": 7208, "count": 0 },
        { "startOffset": 7213, "endOffset": 7391, "count": 0 },
        { "startOffset": 7396, "endOffset": 7571, "count": 0 },
        { "startOffset": 7576, "endOffset": 7756, "count": 0 },
        { "startOffset": 7761, "endOffset": 7940, "count": 0 },
        { "startOffset": 7945, "endOffset": 8133, "count": 0 },
        { "startOffset": 8138, "endOffset": 8318, "count": 0 },
        { "startOffset": 8323, "endOffset": 8526, "count": 0 },
        { "startOffset": 8531, "endOffset": 8723, "count": 0 },
        { "startOffset": 8728, "endOffset": 8925, "count": 0 },
        { "startOffset": 8930, "endOffset": 9123, "count": 0 },
        { "startOffset": 9128, "endOffset": 9326, "count": 0 },
        { "startOffset": 9331, "endOffset": 9524, "count": 0 },
        { "startOffset": 9529, "endOffset": 9727, "count": 0 },
        { "startOffset": 9732, "endOffset": 9921, "count": 0 },
        { "startOffset": 9926, "endOffset": 10115, "count": 0 },
        { "startOffset": 10120, "endOffset": 10311, "count": 0 },
        { "startOffset": 10316, "endOffset": 10507, "count": 0 },
        { "startOffset": 10512, "endOffset": 10706, "count": 0 },
        { "startOffset": 10711, "endOffset": 10904, "count": 0 },
        { "startOffset": 10909, "endOffset": 11102, "count": 0 },
        { "startOffset": 11107, "endOffset": 11305, "count": 0 },
        { "startOffset": 11310, "endOffset": 11504, "count": 0 },
        { "startOffset": 11509, "endOffset": 11708, "count": 0 },
        { "startOffset": 11713, "endOffset": 11909, "count": 0 },
        { "startOffset": 11914, "endOffset": 12115, "count": 0 },
        { "startOffset": 12120, "endOffset": 12316, "count": 0 },
        { "startOffset": 12321, "endOffset": 12522, "count": 0 },
        { "startOffset": 12527, "endOffset": 12719, "count": 0 },
        { "startOffset": 12724, "endOffset": 12916, "count": 0 },
        { "startOffset": 12921, "endOffset": 13115, "count": 0 },
        { "startOffset": 13120, "endOffset": 13314, "count": 0 },
        { "startOffset": 13319, "endOffset": 13514, "count": 0 },
        { "startOffset": 13519, "endOffset": 13719, "count": 0 },
        { "startOffset": 13724, "endOffset": 13919, "count": 0 },
        { "startOffset": 13924, "endOffset": 14124, "count": 0 },
        { "startOffset": 14129, "endOffset": 14324, "count": 0 },
        { "startOffset": 14329, "endOffset": 14529, "count": 0 },
        { "startOffset": 14534, "endOffset": 14729, "count": 0 },
        { "startOffset": 14734, "endOffset": 14934, "count": 0 },
        { "startOffset": 14939, "endOffset": 15134, "count": 0 },
        { "startOffset": 15139, "endOffset": 15339, "count": 0 },
        { "startOffset": 15344, "endOffset": 15539, "count": 0 },
        { "startOffset": 15544, "endOffset": 15744, "count": 0 },
        { "startOffset": 15749, "endOffset": 15944, "count": 0 },
        { "startOffset": 15949, "endOffset": 16149, "count": 0 },
        { "startOffset": 16154, "endOffset": 16349, "count": 0 },
        { "startOffset": 16354, "endOffset": 16554, "count": 0 },
        { "startOffset": 16559, "endOffset": 16756, "count": 0 },
        { "startOffset": 16761, "endOffset": 16963, "count": 0 },
        { "startOffset": 16968, "endOffset": 17165, "count": 0 },
        { "startOffset": 17170, "endOffset": 17372, "count": 0 },
        { "startOffset": 17377, "endOffset": 17574, "count": 0 },
        { "startOffset": 17579, "endOffset": 17781, "count": 0 },
        { "startOffset": 17786, "endOffset": 17985, "count": 0 },
        { "startOffset": 17990, "endOffset": 18194, "count": 0 },
        { "startOffset": 18199, "endOffset": 18398, "count": 0 },
        { "startOffset": 18403, "endOffset": 18607, "count": 0 },
        { "startOffset": 18612, "endOffset": 18811, "count": 0 },
        { "startOffset": 18816, "endOffset": 19020, "count": 0 },
        { "startOffset": 19025, "endOffset": 19104, "count": 0 }
      ],
      "isBlockCoverage": true
    }
  ]
}
